pyaccelsx-0.2.5.dist-info/METADATA
pyaccelsx-0.2.5.dist-info/WHEEL
pyaccelsx-0.2.5.dist-info/licenses/LICENSE.txt
pyaccelsx/__init__.py
pyaccelsx/pyaccelsx.cpython-39-arm-linux-gnueabihf.so
pyaccelsx-0.2.5.dist-info/RECORD
