Metadata-Version: 2.4
Name: pyaccelsx
Version: 0.2.5
Classifier: Programming Language :: Rust
Classifier: Programming Language :: Python :: Implementation :: CPython
Classifier: Programming Language :: Python :: Implementation :: PyPy
License-File: LICENSE.txt
Requires-Python: >=3.8
